MANIFEST.in
README.md
requirements.txt
setup.py
arkhn_monitoring/__init__.py
arkhn_monitoring/logging.py
arkhn_monitoring/metrics.py
arkhn_monitoring.egg-info/PKG-INFO
arkhn_monitoring.egg-info/SOURCES.txt
arkhn_monitoring.egg-info/dependency_links.txt
arkhn_monitoring.egg-info/requires.txt
arkhn_monitoring.egg-info/top_level.txt