Metadata-Version: 2.1
Name: arkhn-monitoring
Version: 0.0.4
Summary: Helper functions used to monitor Arkhn's stack.
Home-page: https://github.com/arkhn/monitoring
Author: Arkhn
Author-email: contact@arkhn.org
License: Apache License 2.0
Platform: UNKNOWN
